rich_menu/__init__.py
rich_menu/menu.py
rich_menu-0.2.0.dist-info/LICENSE
rich_menu-0.2.0.dist-info/METADATA
rich_menu-0.2.0.dist-info/WHEEL
rich_menu-0.2.0.dist-info/RECORD
