Metadata-Version: 2.1
Name: rich-menu
Version: 0.2.0
Summary: 
Author: gbPagano
Author-email: guilhermebpagano@gmail.com
Requires-Python: >=3.10,<4.0
Classifier: Environment :: Console
Classifier: Programming Language :: Python :: 3
Classifier: Programming Language :: Python :: 3.10
Classifier: Programming Language :: Python :: 3.11
Classifier: Programming Language :: Python :: 3.12
Requires-Dist: click (>=8.1.3,<9.0.0)
Requires-Dist: rich (>=13.7.0,<14.0.0)
Project-URL: Code, https://github.com/gbPagano/rich_menu
